pillar/__init__.py
pillar/callbacks.py
pillar/client.py
pillar/context_vars.py
pillar/errors.py
pillar/interceptor/context_hooks/context_framework_adapter.py
pillar/interceptor/context_hooks/context_hook_factory.py
pillar/interceptor/hooks/__init__.py
pillar/interceptor/hooks/framework_adapter.py
pillar/interceptor/hooks/hook_factory.py
pillar/interceptor/hooks/openai/adapter.py
pillar/interceptor/hooks/openai/format_utils.py
pillar/interceptor/hooks/openai/patcher.py
pillar/interceptor/hooks/openai/stream_utils.py
pillar/interceptor/hooks/stream_wrapper.py
pillar/logging.py
pillar/types.py
pillar/utils.py
pillar_security-1.1.4.dist-info/LICENSE
pillar_security-1.1.4.dist-info/METADATA
pillar_security-1.1.4.dist-info/WHEEL
pillar_security-1.1.4.dist-info/RECORD
